amazon_kinesis_utils/__init__.py
amazon_kinesis_utils/baikonur_logging.py
amazon_kinesis_utils/kinesis.py
amazon_kinesis_utils/misc.py
amazon_kinesis_utils/s3.py
amazon_kinesis_utils-0.1.8.dist-info/LICENSE
amazon_kinesis_utils-0.1.8.dist-info/METADATA
amazon_kinesis_utils-0.1.8.dist-info/WHEEL
amazon_kinesis_utils-0.1.8.dist-info/top_level.txt
amazon_kinesis_utils-0.1.8.dist-info/zip-safe
amazon_kinesis_utils-0.1.8.dist-info/RECORD
