Metadata-Version: 2.1
Name: amazon-kinesis-utils
Version: 0.1.8
Summary: amazon-kinesis-utils: a library of useful utilities for Amazon Kinesis
Home-page: https://amazon-kinesis-utils.readthedocs.io/en/latest/
Author: Tamirlan Torgayev
Author-email: torgayev@me.com
License: MIT
Project-URL: Source Code, https://github.com/baikonur-oss/amazon-kinesis-utils
Platform: UNKNOWN
Classifier: Development Status :: 4 - Beta
Classifier: Intended Audience :: Developers
Classifier: License :: OSI Approved :: MIT License
Classifier: Operating System :: OS Independent
Classifier: Programming Language :: Python :: 3
Requires-Dist: python-dateutil
Requires-Dist: aws-kinesis-agg
